topsis/__init__.py
TOPSIS_Jahnvi_101903300-0.0.1.dist-info/LICENSE
TOPSIS_Jahnvi_101903300-0.0.1.dist-info/METADATA
TOPSIS_Jahnvi_101903300-0.0.1.dist-info/WHEEL
TOPSIS_Jahnvi_101903300-0.0.1.dist-info/top_level.txt
TOPSIS_Jahnvi_101903300-0.0.1.dist-info/RECORD
