Metadata-Version: 2.1
Name: TOPSIS-Jahnvi-101903300
Version: 0.0.1
Summary: TOPSIS implementation
Home-page: https://github.com/jahnvi-tanwar/topsis
Author: Jahnvi Tanwar
Author-email: jahnvitanwar3@example.com
License: UNKNOWN
Project-URL: Bug Tracker, https://github.com/jahnvi-tanwar/topsis/issues
Platform: UNKNOWN
Classifier: Programming Language :: Python :: 3
Classifier: License :: OSI Approved :: MIT License
Requires-Python: >=3.6
License-File: LICENSE
